{
  "project_info": {
    "project_number": "826683555027",
    "firebase_url": "https://project-3151073697346267682.firebaseio.com",
    "project_id": "project-3151073697346267682",
    "storage_bucket": "project-3151073697346267682.appspot.com"
  },
  "client": [
    {
      "client_info": {
        "mobilesdk_app_id": "1:826683555027:android:4b29ed417514fdac",
        "android_client_info": {
          "package_name": "com.dii.ids.application"
        }
      },
      "oauth_client": [
        {
          "client_id": "826683555027-1bf4sbn7kdkevdrqsh1bcnjt5tji2jc4.apps.googleusercontent.com",
          "client_type": 3
        }
      ],
      "api_key": [
        {
          "current_key": "AIzaSyBp6DjRNQUgt6O-BQOo1aGSFda4UFDhMxo"
        }
      ],
      "services": {
        "analytics_service": {
          "status": 1
        },
        "appinvite_service": {
          "status": 1,
          "other_platform_oauth_client": []
        },
        "ads_service": {
          "status": 2
        }
      }
    }
  ],
  "configuration_version": "1"
}